mycalc/calculator.py
sunghyuk-0.0.2.dist-info/METADATA
sunghyuk-0.0.2.dist-info/WHEEL
sunghyuk-0.0.2.dist-info/top_level.txt
sunghyuk-0.0.2.dist-info/RECORD
