Metadata-Version: 2.1
Name: sunghyuk
Version: 0.0.2
Summary: oss
Home-page: 
Download-URL: 
Author: sunghyuk
License: UNKNOWN
Platform: UNKNOWN
